TensorflowShenduXuexiZhongwenDierBanChuyiFix1/README.md
TensorflowShenduXuexiZhongwenDierBanChuyiFix1/__init__.py
TensorflowShenduXuexiZhongwenDierBanChuyiFix1/__main__.py
TensorflowShenduXuexiZhongwenDierBanChuyiFix1/file.epub
TensorflowShenduXuexiZhongwenDierBanChuyiFix1/index.html
TensorflowShenduXuexiZhongwenDierBanChuyiFix1/css/__init__.py
TensorflowShenduXuexiZhongwenDierBanChuyiFix1/css/annotations.css
TensorflowShenduXuexiZhongwenDierBanChuyiFix1/css/main.css
TensorflowShenduXuexiZhongwenDierBanChuyiFix1/css/normalize.css
TensorflowShenduXuexiZhongwenDierBanChuyiFix1/css/popup.css
TensorflowShenduXuexiZhongwenDierBanChuyiFix1/font/__init__.py
TensorflowShenduXuexiZhongwenDierBanChuyiFix1/font/fontello.eot
TensorflowShenduXuexiZhongwenDierBanChuyiFix1/font/fontello.svg
TensorflowShenduXuexiZhongwenDierBanChuyiFix1/font/fontello.ttf
TensorflowShenduXuexiZhongwenDierBanChuyiFix1/font/fontello.woff
TensorflowShenduXuexiZhongwenDierBanChuyiFix1/img/__init__.py
TensorflowShenduXuexiZhongwenDierBanChuyiFix1/img/annotator-glyph-sprite.png
TensorflowShenduXuexiZhongwenDierBanChuyiFix1/img/annotator-icon-sprite.png
TensorflowShenduXuexiZhongwenDierBanChuyiFix1/img/apple-touch-icon.png
TensorflowShenduXuexiZhongwenDierBanChuyiFix1/img/cancelfullscreen.png
TensorflowShenduXuexiZhongwenDierBanChuyiFix1/img/close.png
TensorflowShenduXuexiZhongwenDierBanChuyiFix1/img/fullscreen.png
TensorflowShenduXuexiZhongwenDierBanChuyiFix1/img/loader.gif
TensorflowShenduXuexiZhongwenDierBanChuyiFix1/img/menu-icon.png
TensorflowShenduXuexiZhongwenDierBanChuyiFix1/img/save.png
TensorflowShenduXuexiZhongwenDierBanChuyiFix1/img/saved.png
TensorflowShenduXuexiZhongwenDierBanChuyiFix1/img/settings-s.png
TensorflowShenduXuexiZhongwenDierBanChuyiFix1/img/settings.png
TensorflowShenduXuexiZhongwenDierBanChuyiFix1/img/star.png
TensorflowShenduXuexiZhongwenDierBanChuyiFix1/js/__init__.py
TensorflowShenduXuexiZhongwenDierBanChuyiFix1/js/epub.js
tensorflow_shendu_xuexi_zhongwen_dier_ban_chuyi_fix1-2025.3.24.0.dist-info/METADATA
tensorflow_shendu_xuexi_zhongwen_dier_ban_chuyi_fix1-2025.3.24.0.dist-info/WHEEL
tensorflow_shendu_xuexi_zhongwen_dier_ban_chuyi_fix1-2025.3.24.0.dist-info/entry_points.txt
tensorflow_shendu_xuexi_zhongwen_dier_ban_chuyi_fix1-2025.3.24.0.dist-info/top_level.txt
tensorflow_shendu_xuexi_zhongwen_dier_ban_chuyi_fix1-2025.3.24.0.dist-info/RECORD
